{
  "name": "Edgar Morton",
  "age": 33,
  "address": {
    "street": "Weut Circle",
    "city": "Fupawi",
    "state": "ND",
    "zip": "42378"
  },
  "contact": {
    "phone": "(334) 404-4290",
    "servicePhone": "800525319"
  },
  "birthday": "1998-10-07T13:10:05.192Z",
  "ip": "213.186.177.207",
  "foo": "bar",
  "profile": {
    "about": "Voackuj ki hanjuv mo reagise bikup uddog emloset duwde pumlu damkod agoj apimop vibad ukoliz diwdo cacwen bi. Sebitof zuuboes dem siucooz om kujhowim jabmubav vedujava tilsinso wudta jesuk ba. Ughezig junzih uwvih kof sumuv jew nuozo oduguh peiwo ogebade umiv gohhov. Vowiriil effecvos figga zefu lahastum zi dov himues valsiwuk fivto jesuccub esajiwop magralbef miru co.",
    "bio": "Eru oku ucegoreg dit nauhi zuw vitruwju nugezo egulano pusipe bosvav jordakjoj aka. Geluv wipipaj dobac lo kuh kofkemos egmiflo tazsima hum hug wal la mizaho cah sigriru oso anidoj vow. Anafibu botaju jorhuvow zi zo ke jatnolpe kogcegul lig tepfigab zos mopiud sallawi. Elafisu la dit jol naf raufedo lovodu afku gi ucti ovvica maw mejiin rodumita de ashu tulkul. Ruoju fulece zabagim gekvojuci lo san gagla kuhiav vore ri taijsat lucfi iz ke tot ridob teapiaba zav."
  },
  "apiKey": "7c218be1e76aeed35dc8886c0f07519646ee08b77dfe36f7889dea7aae50ecd4",
  "currency": {
    "code": "QAR",
    "name": "Qatar Riyal"
  }
}