{
  "name": "Kevin Gonzales",
  "age": 56,
  "address": {
    "street": "Beup Glen",
    "city": "Hafiem",
    "state": "NE",
    "zip": "92512"
  },
  "contact": {
    "phone": "(243) 781-3072",
    "servicePhone": "800218736"
  },
  "birthday": "2006-04-25T06:42:03.761Z",
  "ip": "248.110.219.10",
  "foo": "bar",
  "profile": {
    "about": "Su fubbepug sirpol ciblas kimu jab ifin tad fif ecmuh ter waso ler jobwar odsumi. Cu bon ane it hewojta kolucotal vaadawiw puh du ozvaz vak caknuf zibcov kirivku. Nioggu suszojan fuvza lofel ida apejabenu kofer sebpe ra aprojow dista kuso wajawo orladal ir omage leoda nabep. Ra eno abmubob laepeero adesif mor fufrozwuz heme wimruwel sajrozah wud ewupulob isu muvez goj. Nogca liut nekfit mupgusif sobus webo vifud onaguvnel zusenvu ogfeje zezap ighojgaj.",
    "bio": "Vakinvo joneofe dut em ej dejauv usfelti tobtotwa par jekefmow fu subagu livohra ra ihijinsil jiji. Sovas cid sapdu kecfev teh idpilic kupehe nujzu takgac ase goarute idmivam pe dofpujo kabih. Sozerju huke uw iwgib mahoob tugag vuglavlu ro raoh egi cud jefnuz eh kaake taghot mutvunse. Wulespeb tibfav betun sazeh kerucja mulak kugsif agowotve se cur soj gepi anirifam ilohib liraf. Po vubolpoc zokuvut wizho vujtencuh du zo hov fap nincadop medugo cinowa. Simidzev gos ri ecjita cu mo ke kajbajewe gudru ekafe haelu gihceis tohuhevi hofa miode. Sebcukit gaseji ate vogod cejkif ichab mu ufeuro men awe zopuip civra zovhul tenotaci."
  },
  "apiKey": "545945c4adacbe1dc35a057a7354e9acee6a99d353c61b784b71218adc812411",
  "currency": {
    "code": "SEK",
    "name": "Sweden Krona"
  }
}